butterfly/__init__.py
butterfly/jwt.py
butterfly_jwt-0.1.0.dist-info/licenses/LICENSE
butterfly_jwt-0.1.0.dist-info/METADATA
butterfly_jwt-0.1.0.dist-info/WHEEL
butterfly_jwt-0.1.0.dist-info/top_level.txt
butterfly_jwt-0.1.0.dist-info/RECORD
